s3bp/__init__.py
s3bp/_version.py
s3bp/core.py
s3bp-0.1.8.dist-info/DESCRIPTION.rst
s3bp-0.1.8.dist-info/METADATA
s3bp-0.1.8.dist-info/RECORD
s3bp-0.1.8.dist-info/WHEEL
s3bp-0.1.8.dist-info/metadata.json
s3bp-0.1.8.dist-info/top_level.txt
