Metadata-Version: 2.0
Name: s3bp
Version: 0.1.8
Summary: Read and write Python objects from/to S3.
Home-page: https://github.com/shaypal5/s3bp
Author: Shay Palachy
Author-email: shaypal5@gmail.com
License: MIT
Keywords: pandas,dataframe,s3
Platform: UNKNOWN
Requires-Dist: botocore
Requires-Dist: boto3
Requires-Dist: python-dateutil
Requires-Dist: pyyaml
Requires-Dist: pandas
Requires-Dist: feather-format
